{
  "kmeans_k3": {
    "representation": "logmel_mean",
    "algorithm": "kmeans",
    "params": {
      "n_clusters": 3
    },
    "valid_runs": 0,
    "total_runs": 7,
    "silhouette_mean": NaN,
    "silhouette_std": NaN,
    "calinski_harabasz_mean": NaN,
    "calinski_harabasz_std": NaN,
    "davies_bouldin_mean": NaN,
    "davies_bouldin_std": NaN,
    "stability": 0.0,
    "quality_score": 0.0,
    "reason": "No valid runs"
  },
  "kmeans_k4": {
    "representation": "logmel_mean",
    "algorithm": "kmeans",
    "params": {
      "n_clusters": 4
    },
    "valid_runs": 0,
    "total_runs": 7,
    "silhouette_mean": NaN,
    "silhouette_std": NaN,
    "calinski_harabasz_mean": NaN,
    "calinski_harabasz_std": NaN,
    "davies_bouldin_mean": NaN,
    "davies_bouldin_std": NaN,
    "stability": 0.0,
    "quality_score": 0.0,
    "reason": "No valid runs"
  },
  "kmeans_k5": {
    "representation": "logmel_mean",
    "algorithm": "kmeans",
    "params": {
      "n_clusters": 5
    },
    "valid_runs": 0,
    "total_runs": 7,
    "silhouette_mean": NaN,
    "silhouette_std": NaN,
    "calinski_harabasz_mean": NaN,
    "calinski_harabasz_std": NaN,
    "davies_bouldin_mean": NaN,
    "davies_bouldin_std": NaN,
    "stability": 0.0,
    "quality_score": 0.0,
    "reason": "No valid runs"
  },
  "hdbscan": {
    "representation": "logmel_mean",
    "algorithm": "hdbscan",
    "params": {
      "min_cluster_size": 3
    },
    "valid_runs": 6,
    "total_runs": 7,
    "silhouette_mean": 0.4348433148474466,
    "silhouette_std": 0.040859141451000905,
    "calinski_harabasz_mean": 165.54743843635663,
    "calinski_harabasz_std": 66.05645922068204,
    "davies_bouldin_mean": 0.5801975833834434,
    "davies_bouldin_std": 0.13133264446297066,
    "stability": 0.9591408585489991,
    "quality_score": 0.41707599033707266,
    "mean_clusters": 4.833333333333333,
    "mean_noise_ratio": 0.3383838383838384
  }
}